ai_git_messages/__init__.py
ai_git_messages/__main__.py
ai_git_messages/_version.py
ai_git_messages/ai_git_messages.py
ai_git_messages-0.0.1.dist-info/METADATA
ai_git_messages-0.0.1.dist-info/WHEEL
ai_git_messages-0.0.1.dist-info/entry_points.txt
ai_git_messages-0.0.1.dist-info/RECORD
