Metadata-Version: 2.4
Name: ai-git-messages
Version: 0.0.1
Summary: CLI tool for generating git messages using AI
Project-URL: homepage, https://github.com/mikegoelzer/ai-git-messages
Project-URL: repository, https://github.com/mikegoelzer/ai-git-messages
Project-URL: documentation, https://github.com/mikegoelzer/ai-git-messages/readme.md
Project-URL: issues, https://github.com/mikegoelzer/ai-git-messages/issues
Author: Mike Goelzer
License: MIT
Classifier: Programming Language :: Python :: 3 :: Only
Requires-Python: >=3.10
Requires-Dist: anthropic>=0.43.0
Requires-Dist: curvpyutils>=0.0.51
Requires-Dist: ollama>=0.4.7
Requires-Dist: pydantic>=2.10.6
Requires-Dist: rich>=13
Provides-Extra: dev
Requires-Dist: pytest>=7.4; extra == 'dev'
